bubblify/__init__.py
bubblify/cli.py
bubblify/core.py
bubblify/gui.py
bubblify-0.1.0.dist-info/METADATA
bubblify-0.1.0.dist-info/WHEEL
bubblify-0.1.0.dist-info/entry_points.txt
bubblify-0.1.0.dist-info/top_level.txt
bubblify-0.1.0.dist-info/RECORD
