Metadata-Version: 2.1
Name: bubblify
Version: 0.1.0
Summary: Interactive URDF spherization tool using Viser for collision approximation
Author-email: Bas van der Heijden <b.heijden@hotmail.com>
License: Apache-2.0
Keywords: robotics,urdf,collision,spherization,viser,gui
Classifier: Programming Language :: Python :: 3
Classifier: Programming Language :: Python :: 3.8
Classifier: Programming Language :: Python :: 3.9
Classifier: Programming Language :: Python :: 3.10
Classifier: Programming Language :: Python :: 3.11
Classifier: Programming Language :: Python :: 3.12
Classifier: License :: OSI Approved :: Apache Software License
Classifier: Operating System :: OS Independent
Classifier: Development Status :: 3 - Alpha
Classifier: Intended Audience :: Science/Research
Classifier: Topic :: Scientific/Engineering :: Visualization
Classifier: Topic :: Software Development :: Libraries :: Python Modules
Requires-Python: >=3.8
Requires-Dist: robot-descriptions>=1.21.0
Requires-Dist: viser>=1.0.8
Requires-Dist: yourdfpy>=0.0.56
Requires-Dist: trimesh>=4.0.0
Requires-Dist: numpy>=1.20.0
